[
    {
        "issue": "NOC-635645",
        "start": "2020-11-17 13:14:00",
        "end": "2020-11-17 16:40:00",
        "scope": "Multiple circuits are down in Northern California",
        "diversity": [
            "Del Norte COE",
            "Lassen COE",
            "Loyalton HS - Sierra COE",
            "Modoc COE",
            "Plumas COE",
            "Siskiyou COE",
            "Tulelake Basin Joint USD"
        ],
        "connectivity": [
            "Feather River College"
        ],
        "vendors_involved": [
            "Environmental"
        ],
        "telco_ticket_id": null,
        "category": "Multi-site",
        "rfo_category": "power outage",
        "rfo_description": ""
    },
    {
        "issue": "NOC-635620",
        "start": "2020-11-17 09:27:00",
        "end": "2020-11-17 09:30:00",
        "scope": "Multiple CVIN circuits bounced.",
        "diversity": [
            "Colusa COE",
            "Sutter COE"
        ],
        "connectivity": [],
        "vendors_involved": [
            "Vast"
        ],
        "telco_ticket_id": null,
        "category": "Multi-site",
        "rfo_category": "unknown",
        "rfo_description": ""
    },
    {
        "issue": "NOC-635571",
        "start": "2020-11-16 21:37:00",
        "end": "2020-11-16 08:31:00",
        "scope": "Solano County Library is back up.",
        "diversity": [],
        "connectivity": [
            "Solano County Library"
        ],
        "vendors_involved": [
            "Environmental"
        ],
        "telco_ticket_id": "294412594",
        "category": "Library",
        "rfo_category": "power outage",
        "rfo_description": ""
    },
    {
        "issue": "NOC-633036",
        "start": "2020-10-26 09:09:00",
        "end": "2020-11-16 13:46:00",
        "scope": "Victor Valley CC - School of Aviation Technology down",
        "diversity": [
            "Victor Valley CCD"
        ],
        "connectivity": [
            "Victor Valley CCD - SCLA School of Aviation Technology"
        ],
        "vendors_involved": [
            "Environmental"
        ],
        "telco_ticket_id": null,
        "category": "CC",
        "rfo_category": "power outage",
        "rfo_description": ""
    },
    {
        "issue": "NOC-635480",
        "start": "2020-11-17 00:30:00",
        "end": "2020-11-17 08:15:00",
        "scope": "Corning Circuits Currently Down",
        "diversity": [
            "Butte Glenn CCD",
            "Del Norte COE",
            "Lassen COE",
            "Loyalton HS - Sierra COE",
            "Modoc COE",
            "Plumas COE",
            "Siskiyou COE",
            "Tulelake Basin Joint USD"
        ],
        "connectivity": [
            "College of the Siskiyous",
            "Shasta Public Library - Redding",
            "Willows Public Library"
        ],
        "vendors_involved": [
            "CENIC Internal"
        ],
        "telco_ticket_id": null,
        "category": "Multi-site",
        "rfo_category": "other",
        "rfo_description": "CENIC maintenance"
    },
    {
        "issue": "NOC-635591",
        "start": "2020-11-17 03:38:00",
        "end": "2020-11-17 03:44:00",
        "scope": "Shasta CC Tehama CPE rebooted.",
        "diversity": [
            "Shasta CC Burney Center",
            "Shasta CCD",
            "Shasta CCD Health Sciences",
            "Shasta CCD Trinity Center"
        ],
        "connectivity": [
            "Shasta CC - Tehama"
        ],
        "vendors_involved": [
            "Environmental"
        ],
        "telco_ticket_id": null,
        "category": "CC",
        "rfo_category": "power outage",
        "rfo_description": ""
    },
    {
        "issue": "NOC-635524",
        "start": "2020-11-16 12:02:00",
        "end": "2020-11-16 12:05:00",
        "scope": "Multiple circuits bounced in the San Diego area.",
        "diversity": [
            "CSU San Marcos"
        ],
        "connectivity": [
            "San Diego County Library - El Cajon"
        ],
        "vendors_involved": [
            "AT&T"
        ],
        "telco_ticket_id": "LE128021,  LE128023",
        "category": "Multi-site",
        "rfo_category": "unknown",
        "rfo_description": ""
    },
    {
        "issue": "NOC-635481",
        "start": "2020-11-16 01:13:00",
        "end": "2020-11-16 01:16:00",
        "scope": "Corona Public Library Down",
        "diversity": [],
        "connectivity": [
            "Corona Public Library"
        ],
        "vendors_involved": [
            "Environmental"
        ],
        "telco_ticket_id": null,
        "category": "Library",
        "rfo_category": "power outage",
        "rfo_description": ""
    },
    {
        "issue": "NOC-635460",
        "start": "2020-11-15 15:58:00",
        "end": "2020-11-15 15:59:00",
        "scope": "UCSF Health System circuit bounce",
        "diversity": [],
        "connectivity": [],
        "vendors_involved": [
            "Zayo"
        ],
        "telco_ticket_id": "Case # TTN-0004589455",
        "category": "UC",
        "rfo_category": "unknown",
        "rfo_description": ""
    },
    {
        "issue": "NOC-635298",
        "start": "2020-11-14 03:16:00",
        "end": "2020-11-14 10:18:00",
        "scope": "UCANR Elkus Ranch REC is unreachable.",
        "diversity": [],
        "connectivity": [
            "UCANR Elkus Ranch REC"
        ],
        "vendors_involved": [
            "Environmental"
        ],
        "telco_ticket_id": "294023444",
        "category": "UC",
        "rfo_category": "power outage",
        "rfo_description": ""
    },
    {
        "issue": "NOC-635409",
        "start": "2020-11-13 21:04:00",
        "end": "2020-11-13 22:55:00",
        "scope": "San Francisco Public Library (Leland) is unreachable.",
        "diversity": [],
        "connectivity": [
            "San Francisco Public Library"
        ],
        "vendors_involved": [
            "AT&T"
        ],
        "telco_ticket_id": "294117041",
        "category": "Library",
        "rfo_category": "faulty line card",
        "rfo_description": ""
    },
    {
        "issue": "NOC-635413",
        "start": "2020-11-13 21:00:00",
        "end": "2020-11-13 22:55:00",
        "scope": "Skyline CCD 10GE Circuit to Oakland Hub is down.",
        "diversity": [
            "Skyline College"
        ],
        "connectivity": [],
        "vendors_involved": [
            "AT&T"
        ],
        "telco_ticket_id": "294119799",
        "category": "CC",
        "rfo_category": "faulty line card",
        "rfo_description": ""
    },
    {
        "issue": "NOC-635308",
        "start": "2020-11-13 01:04:00",
        "end": "2020-11-13 23:15:00",
        "scope": "Sutro Library is unreachable.",
        "diversity": [],
        "connectivity": [
            "Sutro Library"
        ],
        "vendors_involved": [
            "AT&T"
        ],
        "telco_ticket_id": "294040107",
        "category": "Library",
        "rfo_category": "faulty line card",
        "rfo_description": ""
    },
    {
        "issue": "NOC-635392",
        "start": "2020-11-13 16:44:00",
        "end": "2020-11-13 23:45:00",
        "scope": "Multiple circuits are down in Bay Area.",
        "diversity": [
            "Contra Costa COE"
        ],
        "connectivity": [
            "Alameda COE",
            "Oakland USD"
        ],
        "vendors_involved": [
            "Comcast"
        ],
        "telco_ticket_id": "Si046586459",
        "category": "Multi-site",
        "rfo_category": "fiber damage",
        "rfo_description": ""
    },
    {
        "issue": "NOC-635357",
        "start": "2020-11-13 07:23:00",
        "end": "2020-11-13 08:46:00",
        "scope": "Humboldt County Library is unreachable",
        "diversity": [],
        "connectivity": [
            "Humboldt County Library"
        ],
        "vendors_involved": [
            "Environmental"
        ],
        "telco_ticket_id": "294069410",
        "category": "Library",
        "rfo_category": "power outage",
        "rfo_description": ""
    },
    {
        "issue": "NOC-635298",
        "start": "2020-11-12 20:10:00",
        "end": "2020-11-13 08:49:00",
        "scope": "UCANR Elkus Ranch REC unreachable.",
        "diversity": [],
        "connectivity": [
            "UCANR Elkus Ranch REC"
        ],
        "vendors_involved": [
            "Environmental"
        ],
        "telco_ticket_id": "294023444",
        "category": "UC",
        "rfo_category": "power outage",
        "rfo_description": ""
    },
    {
        "issue": "NOC-635254",
        "start": "2020-11-12 12:07:00",
        "end": "2020-11-12 19:19:00",
        "scope": "UCANR Inter-Mountain REC is currently unavailable.",
        "diversity": [],
        "connectivity": [
            "UCANR Inter-Mountain REC"
        ],
        "vendors_involved": [
            "Hunter Communications"
        ],
        "telco_ticket_id": "133790787",
        "category": "UC",
        "rfo_category": "fiber damage",
        "rfo_description": ""
    },
    {
        "issue": "NOC-635331",
        "start": "2020-11-13 03:26:00",
        "end": "2020-11-13 03:44:00",
        "scope": "Multiple AT&T circuits went down in NorCal area.",
        "diversity": [
            "Butte COE",
            "College of the Siskiyous",
            "Del Norte COE",
            "Glenn COE - Orland",
            "Lassen COE",
            "Loyalton HS - Sierra COE",
            "Modoc COE",
            "Shasta CC - Tehama",
            "Shasta CC Burney Center",
            "Shasta CCD",
            "Shasta CCD Health Sciences",
            "Shasta CCD Trinity Center",
            "Shasta COE",
            "Siskiyou COE",
            "Trinity COE",
            "Tulelake Basin Joint USD"
        ],
        "connectivity": [
            "Tehama COE"
        ],
        "vendors_involved": [
            "AT&T"
        ],
        "telco_ticket_id": null,
        "category": "Multi-site",
        "rfo_category": "higher level carrier",
        "rfo_description": ""
    },
    {
        "issue": "NOC-635316",
        "start": "2020-11-13 02:45:00",
        "end": "2020-11-13 02:50:00",
        "scope": "Multiple Dark Fiber circuits are unstable in the Southern California region.",
        "diversity": [
            "Orange County Department of Education",
            "University of California, Irvine"
        ],
        "connectivity": [
            "Los Angeles USD - Van Nuys"
        ],
        "vendors_involved": [
            "Crown Castle"
        ],
        "telco_ticket_id": "CCF20348370 CCF20348371 CCF20348372 CCF20347713 CCF20348373",
        "category": "Multi-site",
        "rfo_category": "unknown",
        "rfo_description": ""
    },
    {
        "issue": "NOC-635310",
        "start": "2020-11-13 01:32:00",
        "end": "2020-11-13 03:29:00",
        "scope": "The circuits between Del Norte COE and Siskiyou COE are down.",
        "diversity": [
            "Del Norte COE",
            "Lassen COE",
            "Loyalton HS - Sierra COE",
            "Modoc COE",
            "Plumas COE",
            "Siskiyou COE",
            "Tulelake Basin Joint USD"
        ],
        "connectivity": [],
        "vendors_involved": [
            "Frontier"
        ],
        "telco_ticket_id": "2874437 /  2874440",
        "category": "K12/COE",
        "rfo_category": "higher level carrier",
        "rfo_description": ""
    },
    {
        "issue": "NOC-635337",
        "start": "2020-11-13 03:39:00",
        "end": "2020-11-13 03:43:00",
        "scope": "Shasta CC Trinity Center was briefly unavailable.",
        "diversity": [
            "Shasta CC - Tehama",
            "Shasta CC Burney Center",
            "Shasta CCD",
            "Shasta CCD Health Sciences"
        ],
        "connectivity": [
            "Shasta CCD Trinity Center"
        ],
        "vendors_involved": [
            "Frontier"
        ],
        "telco_ticket_id": null,
        "category": "CC",
        "rfo_category": "provider maintenance",
        "rfo_description": ""
    },
    {
        "issue": "NOC-635250",
        "start": "2020-11-12 12:00:00",
        "end": "2020-11-12 17:23:00",
        "scope": "UCSF Health System circuit down",
        "diversity": [],
        "connectivity": [],
        "vendors_involved": [
            "Zayo"
        ],
        "telco_ticket_id": "TTN-0004584425",
        "category": "UC",
        "rfo_category": "fiber cut",
        "rfo_description": ""
    },
    {
        "issue": "NOC-635221",
        "start": "2020-11-12 06:59:00",
        "end": "2020-11-12 07:32:00",
        "scope": "Multiple circuits down in Fresno",
        "diversity": [
            "Central Valley Independent Network",
            "Chowchilla USD",
            "Coalinga District Library",
            "College of the Sequoias - Hanford Campus",
            "College of the Sequoias - Tulare Campus",
            "College of the Sequoias CCD",
            "CSU Bakersfield",
            "CSU Fresno",
            "Earlimart School District",
            "Fresno City College",
            "Fresno County Library",
            "Kern CCD",
            "Kern COE",
            "Madera COE",
            "Madera County Library",
            "Mariposa County Library",
            "Merced CC",
            "Merced COE",
            "Merced County Library",
            "San Joaquin COE",
            "San Joaquin Delta College",
            "San Luis Obispo COE",
            "Stanislaus COE",
            "State Center CCD (Fresno)",
            "Taft College",
            "Tulare COE",
            "Tulare County Library",
            "Tulare Public Library",
            "West Hills CCD",
            "West Hills Lemoore CC",
            "West Hills North District Center CC"
        ],
        "connectivity": [
            "Ceres Unified School District",
            "Kern County Library",
            "Kings County Library",
            "Porterville College"
        ],
        "vendors_involved": [
            "Vast"
        ],
        "telco_ticket_id": null,
        "category": "Multi-site",
        "rfo_category": "faulty line card",
        "rfo_description": ""
    },
    {
        "issue": "NOC-635178",
        "start": "2020-11-11 15:57:00",
        "end": "2020-11-12 12:24:00",
        "scope": "The circuit between Shasta CC and the Tehama campus is unstable.",
        "diversity": [
            "Shasta CC - Tehama",
            "Shasta CC Burney Center",
            "Shasta CCD",
            "Shasta CCD Health Sciences",
            "Shasta CCD Trinity Center"
        ],
        "connectivity": [],
        "vendors_involved": [
            "AT&T"
        ],
        "telco_ticket_id": "293910501",
        "category": "CC",
        "rfo_category": "faulty line card",
        "rfo_description": ""
    },
    {
        "issue": "NOC-635209",
        "start": "2020-11-12 02:23:00",
        "end": "2020-11-12 06:24:00",
        "scope": "Riverside Public Library is unreachable.",
        "diversity": [],
        "connectivity": [
            "Riverside Public Library"
        ],
        "vendors_involved": [
            "AT&T"
        ],
        "telco_ticket_id": "YK003958",
        "category": "Library",
        "rfo_category": "faulty line card",
        "rfo_description": ""
    },
    {
        "issue": "NOC-635113",
        "start": "2020-11-11 21:54:00",
        "end": "2020-11-11 21:56:00",
        "scope": "Orange County Dept of Education dark fiber circuit unstable.",
        "diversity": [
            "Orange County Department of Education"
        ],
        "connectivity": [],
        "vendors_involved": [
            "Crown Castle"
        ],
        "telco_ticket_id": null,
        "category": "K12/COE",
        "rfo_category": "unknown",
        "rfo_description": ""
    },
    {
        "issue": "NOC-635182",
        "start": "2020-11-11 17:29:00",
        "end": "2020-11-11 19:04:00",
        "scope": "UCANR Hansen REC is unavailable.",
        "diversity": [],
        "connectivity": [
            "UCANR Hansen REC"
        ],
        "vendors_involved": [
            "GeoLinks"
        ],
        "telco_ticket_id": "SS-11111002",
        "category": "UC",
        "rfo_category": "higher level carrier",
        "rfo_description": ""
    },
    {
        "issue": "NOC-635166",
        "start": "2020-11-11 13:24:00",
        "end": "2020-11-11 13:45:00",
        "scope": "Multiple circuits dropped in Southern California",
        "diversity": [
            "Long Beach City College",
            "Long Beach PCC"
        ],
        "connectivity": [
            "Santa Clarita Public Library"
        ],
        "vendors_involved": [
            "AT&T"
        ],
        "telco_ticket_id": "LE127827",
        "category": "Multi-site",
        "rfo_category": "unknown",
        "rfo_description": ""
    },
    {
        "issue": "NOC-635128",
        "start": "2020-11-11 03:00:00",
        "end": "2020-11-11 11:51:00",
        "scope": "Two 10GE circuits are available following migration troubleshooting.",
        "diversity": [
            "Calaveras COE",
            "Yuba COE"
        ],
        "connectivity": [],
        "vendors_involved": [
            "CENIC Internal"
        ],
        "telco_ticket_id": null,
        "category": "Multi-site",
        "rfo_category": "other",
        "rfo_description": "CENIC maintenance"
    },
    {
        "issue": "NOC-635148",
        "start": "2020-11-11 08:57:00",
        "end": "2020-11-11 09:05:00",
        "scope": "Multiple circuits in the Tustin area were down briefly.",
        "diversity": [
            "CSU Los Angeles",
            "LA Valley College",
            "Los Angeles COE"
        ],
        "connectivity": [],
        "vendors_involved": [
            "AT&T"
        ],
        "telco_ticket_id": "YK003954 - YK003956",
        "category": "Multi-site",
        "rfo_category": "faulty line card",
        "rfo_description": ""
    },
    {
        "issue": "NOC-635113",
        "start": "2020-11-11 00:46:00",
        "end": "2020-11-11 01:06:00",
        "scope": "Orange County Department of Education dark fiber to Los Angeles hubsite is unstable.",
        "diversity": [
            "Orange County Department of Education"
        ],
        "connectivity": [],
        "vendors_involved": [
            "Crown Castle"
        ],
        "telco_ticket_id": null,
        "category": "K12/COE",
        "rfo_category": "unknown",
        "rfo_description": ""
    },
    {
        "issue": "NOC-635121",
        "start": "2020-11-11 01:30:00",
        "end": "2020-11-11 01:42:00",
        "scope": "Norco CC was down.",
        "diversity": [
            "Moreno Valley College",
            "Riverside CCD"
        ],
        "connectivity": [
            "Norco CC"
        ],
        "vendors_involved": [
            "AT&T"
        ],
        "telco_ticket_id": null,
        "category": "Multi-site",
        "rfo_category": "faulty line card",
        "rfo_description": ""
    }
]