[
    {
        "issue": "NOC-639579",
        "start": "2021-01-11 13:20:00",
        "end": "2021-01-11 13:47:00",
        "scope": "Brief instability on Riverside CC connections.",
        "diversity": [
            "Moreno Valley College",
            "Norco CC",
            "Riverside CCD"
        ],
        "connectivity": [],
        "vendors_involved": [
            "AT&T"
        ],
        "telco_ticket_id": null,
        "category": "CC",
        "rfo_category": "unknown",
        "rfo_description": ""
    },
    {
        "issue": "NOC-639426",
        "start": "2021-01-09 11:45:00",
        "end": "2021-01-11 11:34:00",
        "scope": "Los Gatos Public Library restored",
        "diversity": [],
        "connectivity": [
            "Los Gatos Public Library"
        ],
        "vendors_involved": [
            "AT&T"
        ],
        "telco_ticket_id": "296131914-GCSC, FE150329-ENOC",
        "category": "Library",
        "rfo_category": "faulty line card",
        "rfo_description": ""
    },
    {
        "issue": "NOC-639524",
        "start": "2021-01-11 01:48:00",
        "end": "2021-01-11 01:54:00",
        "scope": "Los Angeles USD - Van Nuys 100G to Tustin Briefly Down",
        "diversity": [],
        "connectivity": [
            "Los Angeles USD - Van Nuys"
        ],
        "vendors_involved": [
            "Crown Castle"
        ],
        "telco_ticket_id": "CCF21362711",
        "category": "K12/COE",
        "rfo_category": "provider maintenance",
        "rfo_description": "Due to unrelated maintenance"
    },
    {
        "issue": "NOC-639520",
        "start": "2021-01-11 00:35:00",
        "end": "2021-01-11 00:49:00",
        "scope": "Circuit bounced due to maintenance activity.",
        "diversity": [
            "Cal Poly San Luis Obispo",
            "Carnegie Mellon University West"
        ],
        "connectivity": [],
        "vendors_involved": [
            "CENIC Internal"
        ],
        "telco_ticket_id": null,
        "category": "CSU",
        "rfo_category": "other",
        "rfo_description": "CENIC maintenance"
    },
    {
        "issue": "NOC-639495",
        "start": "2021-01-10 13:08:00",
        "end": "2021-01-10 13:12:00",
        "scope": "10GE circuit to Oakland Outage",
        "diversity": [
            "Santa Clara County Library District"
        ],
        "connectivity": [],
        "vendors_involved": [
            "AT&T"
        ],
        "telco_ticket_id": "296149291",
        "category": "Library",
        "rfo_category": "unknown",
        "rfo_description": ""
    },
    {
        "issue": "NOC-639374",
        "start": "2021-01-08 13:35:00",
        "end": "2021-01-08 13:40:00",
        "scope": "100GE circuit between CSU Sacramento and Sacramento hubsite has restored.",
        "diversity": [
            "CSU Sacramento"
        ],
        "connectivity": [],
        "vendors_involved": [
            "CenturyLink (Level3)"
        ],
        "telco_ticket_id": null,
        "category": "Multi-site",
        "rfo_category": "unknown",
        "rfo_description": ""
    },
    {
        "issue": "NOC-639369",
        "start": "2021-01-08 10:52:00",
        "end": "2021-01-08 10:54:00",
        "scope": "The 1GE and 10GE circuits to Oakland and Sunnyvale are stable.",
        "diversity": [],
        "connectivity": [
            "College of the Alameda Science Annex Center"
        ],
        "vendors_involved": [
            "AT&T"
        ],
        "telco_ticket_id": null,
        "category": "CC",
        "rfo_category": "unknown",
        "rfo_description": ""
    },
    {
        "issue": "NOC-639338",
        "start": "2021-01-08 01:46:00",
        "end": "2021-01-08 03:03:00",
        "scope": "Circuit between Modoc COE and Tulelake Basin Joint USD is down.",
        "diversity": [
            "Del Norte COE",
            "Lassen COE",
            "Loyalton HS - Sierra COE",
            "Modoc COE",
            "Plumas COE",
            "Siskiyou COE",
            "Tulelake Basin Joint USD"
        ],
        "connectivity": [],
        "vendors_involved": [
            "Cal-Ore"
        ],
        "telco_ticket_id": "26158296",
        "category": "Multi-site",
        "rfo_category": "faulty line card",
        "rfo_description": ""
    },
    {
        "issue": "NOC-639329",
        "start": "2021-01-07 23:49:00",
        "end": "2021-01-08 00:02:00",
        "scope": "100G circuit is down.",
        "diversity": [],
        "connectivity": [
            "Los Angeles Public Library"
        ],
        "vendors_involved": [
            "Crown Castle"
        ],
        "telco_ticket_id": null,
        "category": "Library",
        "rfo_category": "provider maintenance",
        "rfo_description": "Unrelated provider maintenance"
    },
    {
        "issue": "NOC-639323",
        "start": "2021-01-07 22:39:00",
        "end": "2021-01-07 23:51:00",
        "scope": "Chaffey Joint UHSD dark fiber to Los Angeles hubsite unstable.",
        "diversity": [
            "Chaffey Joint UHSD",
            "San Bernardino CSS"
        ],
        "connectivity": [],
        "vendors_involved": [
            "Crown Castle"
        ],
        "telco_ticket_id": null,
        "category": "Multi-site",
        "rfo_category": "other",
        "rfo_description": "Unrelated provider maintenance"
    },
    {
        "issue": "NOC-639188",
        "start": "2021-01-06 18:49:00",
        "end": "2021-01-07 08:50:00",
        "scope": "West Hills North District Center router down",
        "diversity": [
            "West Hills North District Center CC"
        ],
        "connectivity": [],
        "vendors_involved": [
            "Environmental"
        ],
        "telco_ticket_id": null,
        "category": "CC",
        "rfo_category": "power outage",
        "rfo_description": ""
    },
    {
        "issue": "NOC-639286",
        "start": "2021-01-07 13:14:00",
        "end": "2021-01-07 13:17:00",
        "scope": "Cuesta CC 10GE circuit to Cuesta CC North Campus is up.",
        "diversity": [
            "Cuesta College",
            "Cuesta College North County Campus"
        ],
        "connectivity": [],
        "vendors_involved": [
            "AT&T"
        ],
        "telco_ticket_id": null,
        "category": "CC",
        "rfo_category": "unknown",
        "rfo_description": ""
    },
    {
        "issue": "NOC-639264",
        "start": "2021-01-07 10:08:00",
        "end": "2021-01-07 10:09:00",
        "scope": "Multiple Comcast circuits are up.",
        "diversity": [
            "Contra Costa CCDO",
            "Shasta CCD"
        ],
        "connectivity": [
            "City of Alameda",
            "Contra Costa CCDO",
            "El Dorado County Library - Cameron Park Library",
            "El Dorado County Library - El Dorado Hills Branch",
            "El Dorado County Library - Pollock Pines Branch",
            "Orland Free Library"
        ],
        "vendors_involved": [
            "Comcast"
        ],
        "telco_ticket_id": null,
        "category": "Multi-site",
        "rfo_category": "unknown",
        "rfo_description": ""
    },
    {
        "issue": "NOC-639226",
        "start": "2021-01-07 02:54:00",
        "end": "2021-01-07 03:36:00",
        "scope": "Multiple AT&T Circuits down.",
        "diversity": [
            "Lake Tahoe CC",
            "Yuba CC",
            "Yuba CCD - Sutter County Center"
        ],
        "connectivity": [],
        "vendors_involved": [
            "AT&T"
        ],
        "telco_ticket_id": null,
        "category": "Multi-site",
        "rfo_category": "other",
        "rfo_description": "Unannounced maintenance"
    },
    {
        "issue": "NOC-639238",
        "start": "2021-01-07 05:14:00",
        "end": "2021-01-07 05:16:00",
        "scope": "Multiple AT&T circuits bounced.",
        "diversity": [
            "Garfield Center",
            "Glendale CC Professional Development Center",
            "Glendale CCD"
        ],
        "connectivity": [
            "Altadena Public Library",
            "Sierra Madre Public Library"
        ],
        "vendors_involved": [
            "AT&T"
        ],
        "telco_ticket_id": null,
        "category": "Multi-site",
        "rfo_category": "other",
        "rfo_description": "Power failure at CO"
    },
    {
        "issue": "NOC-638965",
        "start": "2021-01-04 17:22:00",
        "end": "2021-01-06 16:42:00",
        "scope": "Loss of connectivity to UCANR Hansen REC site.",
        "diversity": [],
        "connectivity": [
            "UCANR Hansen REC"
        ],
        "vendors_involved": [
            "GeoLinks"
        ],
        "telco_ticket_id": "163680",
        "category": "UC",
        "rfo_category": "faulty line card",
        "rfo_description": ""
    },
    {
        "issue": "NOC-638739",
        "start": "2020-12-30 17:31:00",
        "end": "2021-01-06 15:24:00",
        "scope": "Feather River CC backup DS3 down.",
        "diversity": [
            "Feather River College"
        ],
        "connectivity": [],
        "vendors_involved": [
            "CENIC Internal"
        ],
        "telco_ticket_id": null,
        "category": "CC",
        "rfo_category": "other",
        "rfo_description": "DS3 cut during CENIC maintenance"
    },
    {
        "issue": "NOC-639166",
        "start": "2021-01-06 13:39:00",
        "end": "2021-01-06 14:47:00",
        "scope": "Loss connectivity to Copper Mountain CCD.",
        "diversity": [
            "College of the Desert"
        ],
        "connectivity": [
            "Copper Mountain CCD"
        ],
        "vendors_involved": [
            "Environmental"
        ],
        "telco_ticket_id": "ECT-80457275",
        "category": "CC",
        "rfo_category": "power outage",
        "rfo_description": ""
    },
    {
        "issue": "NOC-639164",
        "start": "2021-01-06 13:21:00",
        "end": "2021-01-06 13:36:00",
        "scope": "San Diego COE 100GE to San Diego (SAND1) hubsite is stable.",
        "diversity": [
            "San Diego COE"
        ],
        "connectivity": [],
        "vendors_involved": [
            "Crown Castle"
        ],
        "telco_ticket_id": "CCF21361851",
        "category": "K12/COE",
        "rfo_category": "other",
        "rfo_description": "Due to unrelated maintenance"
    },
    {
        "issue": "NOC-639127",
        "start": "2021-01-06 09:34:00",
        "end": "2021-01-06 13:10:00",
        "scope": "Mira Costa CC - Learning Center is down.",
        "diversity": [
            "MiraCosta College",
            "MiraCosta College San Elijo Campus"
        ],
        "connectivity": [
            "Mira Costa College Community Learning Center"
        ],
        "vendors_involved": [
            "Environmental"
        ],
        "telco_ticket_id": null,
        "category": "CC",
        "rfo_category": "power outage",
        "rfo_description": ""
    },
    {
        "issue": "NOC-639146",
        "start": "2021-01-06 11:19:00",
        "end": "2021-01-06 11:37:00",
        "scope": "LA Pierce College was briefly unavailable.",
        "diversity": [],
        "connectivity": [
            "LA Pierce College"
        ],
        "vendors_involved": [
            "Environmental"
        ],
        "telco_ticket_id": null,
        "category": "CC",
        "rfo_category": "power outage",
        "rfo_description": ""
    },
    {
        "issue": "NOC-639091",
        "start": "2021-01-06 00:05:00",
        "end": "2021-01-06 00:34:00",
        "scope": "Camarillo Public Library down",
        "diversity": [],
        "connectivity": [
            "Camarillo Public Library"
        ],
        "vendors_involved": [
            "Spectrum"
        ],
        "telco_ticket_id": null,
        "category": "Library",
        "rfo_category": "other",
        "rfo_description": "Unannounced maintenance"
    },
    {
        "issue": "NOC-639084",
        "start": "2021-01-05 22:34:00",
        "end": "2021-01-05 23:28:00",
        "scope": "Southwestern CCD HEC - Otay Mesa Currently Down Due Unplanned to Power Loss",
        "diversity": [],
        "connectivity": [
            "Southwestern CCD HEC - Otay Mesa"
        ],
        "vendors_involved": [
            "Environmental"
        ],
        "telco_ticket_id": null,
        "category": "CC",
        "rfo_category": "power outage",
        "rfo_description": ""
    }
]